setup.py
milkman/__init__.py
milkman/dairy.py
milkman/generators.py
milkman.egg-info/PKG-INFO
milkman.egg-info/SOURCES.txt
milkman.egg-info/dependency_links.txt
milkman.egg-info/not-zip-safe
milkman.egg-info/requires.txt
milkman.egg-info/top_level.txt
testapp/__init__.py
testapp/manage.py
testapp/models.py
testapp/settings.py
testapp/tests.py