Metadata-Version: 1.0
Name: milkman
Version: 0.5
Summary: Testing Django without all the fixtures
Home-page: http://github.com/ccollins/milkman/
Author: Wilkes Joiner, Chuck Collins, Patrick Altman
Author-email: chuck.collins@gmail.com
License: BSD
Keywords: django testing mock stub
Platform: UNKNOWN
